vb_constants/__init__.py
vb_constants/__main__.py
vb_constants/main.py
vb_constants/modern_physics.py
vb_constants-0.1.0.dist-info/METADATA
vb_constants-0.1.0.dist-info/WHEEL
vb_constants-0.1.0.dist-info/RECORD
