Metadata-Version: 2.1
Name: vb-constants
Version: 0.1.0
Summary: Constants of physics.
Author: vaibhavblayer
Author-email: vaibhavblayer@gmail.com
Requires-Python: >=3.11,<4.0
Classifier: Programming Language :: Python :: 3
Classifier: Programming Language :: Python :: 3.11
